tiffeditor.py
tiffeditor-0.4.0.dist-info/LICENSE
tiffeditor-0.4.0.dist-info/METADATA
tiffeditor-0.4.0.dist-info/WHEEL
tiffeditor-0.4.0.dist-info/entry_points.txt
tiffeditor-0.4.0.dist-info/RECORD
