Metadata-Version: 2.3
Name: tiffeditor
Version: 0.4.0
Summary: メモリ効率の良い巨大TIFF画像の部分編集ライブラリ
License: MIT
Keywords: tiff,image,editing,opencv,memory-efficient
Author: Masakazu Matsumoto
Author-email: vitroid@gmail.com
Requires-Python: >=3.11,<4.0
Classifier: Development Status :: 4 - Beta
Classifier: Intended Audience :: Developers
Classifier: License :: OSI Approved :: MIT License
Classifier: Programming Language :: Python :: 3
Classifier: Programming Language :: Python :: 3.11
Classifier: Programming Language :: Python :: 3.12
Classifier: Programming Language :: Python :: 3.13
Classifier: Topic :: Multimedia :: Graphics :: Graphics Conversion
Classifier: Topic :: Scientific/Engineering :: Image Processing
Requires-Dist: numpy (>=2.0.0,<3.0.0)
Requires-Dist: opencv-python-headless (>=4.12.0.88,<5.0.0.0)
Requires-Dist: psutil (>=7.1.0,<8.0.0)
Requires-Dist: pyperbox (>=0.1.1,<0.2.0)
Requires-Dist: rasterio (>=1.4.3,<2.0.0)
Requires-Dist: tifffile (>=2025.9.9,<2026.0.0)
Project-URL: Documentation, https://github.com/vitroid/tiffeditor
Project-URL: Homepage, https://github.com/vitroid/tiffeditor
Project-URL: Repository, https://github.com/vitroid/tiffeditor
